[
    {
        "Name": "DXVisitor",
        "Value": "207451ff-5808-4a9d-9f39-8f58551bd95c",
        "Expires": "1/1/0001 12:00:00 AM",
        "Secure": "False",
        "Domain": "",
    },
    {
        "Name": "_ga",
        "Value": "GA1.2.2047330150.1560660620",
        "Expires": "1/1/0001 12:00:00 AM",
        "Secure": "False",
        "Domain": "",
    },
    {
        "Name": "__lc.visitor_id.4103151",
        "Value": "S1560660622.537372975a",
        "Expires": "1/1/0001 12:00:00 AM",
        "Secure": "False",
        "Domain": "",
    },
    {
        "Name": "dxMsg",
        "Value": "%5B%7B%22Id%22%3A%22cookie-info%22%2C%22Minimized%22%3Afalse%2C%22Processed%22%3Atrue%2C%22Expires%22%3A%222050-01-01T08%3A00%3A00Z%22%7D%5D",
        "Expires": "1/1/0001 12:00:00 AM",
        "Secure": "False",
        "Domain": "",
    }
]